streamlit_charts/__init__.py
streamlit_charts-0.1.1.dist-info/LICENSE
streamlit_charts-0.1.1.dist-info/METADATA
streamlit_charts-0.1.1.dist-info/WHEEL
streamlit_charts-0.1.1.dist-info/top_level.txt
streamlit_charts-0.1.1.dist-info/RECORD
