Metadata-Version: 2.1
Name: streamlit-charts
Version: 0.1.1
Summary: Render Ant Design Charts in Streamlit
Home-page: https://github.com/lxfu1/streamlit-charts
Author: lxuf1
Author-email: 954055752@qq.com
Keywords: antv,charts,Ant Design Charts,streamlit-component,streamlit-charts
Requires-Python: >=3.8
License-File: LICENSE
Requires-Dist: streamlit >=0.63
